{"0":{"0":"EMILIO J. MANSO","1":"9","2":"9.1","3":"ANDALUCIA OPEN FUTURE","4":"CONSEJERIA DE ECONOMIA, CONOCIMIENTO, EMPRESAS Y UNIVERSIDAD EN COLABORACI\u00d3N CON TELEF\u00d3NICA","5":"ANDALUCIA@OPENFUTURE.ORG","6":"2013","7":"ACTUALIDAD","8":"SI","9":"INST","10":"ANDALUCIA","11":"ANDALUCIA","12":"1","13":"1","14":"","15":"1","16":"1","17":"","18":"1","19":"","20":"1","21":"1","22":"","23":"","24":"","25":"","26":"","27":"","28":"","29":"","30":"1","31":"","32":"","33":"","34":"","35":"","36":"","37":"1","38":"1","39":"","40":"","41":"","42":"","43":"","44":"","45":"","46":""},"1":{"0":"EMILIO J. MANSO","1":"9","2":"9.2","3":"SUD SOSTENIBLE (SISTEMAS URBANOS DE DRENAJE SOSTENIBLE)","4":"CONSEJERIA AGRICULTURA, GANADER\u00cdA, PESCA Y DESARROLLO SOSTENIBLE","5":"ANA ABELL\u00c1N","6":"2016","7":"ACTUALIDAD","8":"SI","9":"INST","10":"ANDALUCIA","11":"ANDALUCIA","12":"1","13":"","14":"","15":"","16":"","17":"","18":"","19":"","20":"","21":"","22":"","23":"","24":"","25":"","26":"","27":"","28":"","29":"","30":"","31":"","32":"","33":"","34":"","35":"1","36":"","37":"","38":"","39":"","40":"","41":"","42":"","43":"","44":"1","45":"","46":""},"2":{"0":"EMILIO J. MANSO","1":"9","2":"9.3","3":"LIVING LAB SALUD ANDALUCIA","4":"CONSEJERIA DE INNOVACION, CIENCIA Y EMPRESA Y DE SALUD","5":"JUAN LAGO (JUAN.LAGO@IAVANTE.ES)","6":"2008","7":"","8":"SI","9":"INST","10":"ANDALUCIA","11":"ANDALUCIA","12":"1","13":"","14":"","15":"1","16":"1","17":"","18":"1","19":"","20":"1","21":"","22":"","23":"","24":"","25":"","26":"","27":"","28":"","29":"","30":"1","31":"","32":"","33":"","34":"","35":"","36":"","37":"1","38":"1","39":"1","40":"","41":"","42":"","43":"","44":"","45":"","46":""},"3":{"0":"EMILIO J. MANSO","1":"9","2":"9.4","3":"PROGRAMA ADE (ACELERADORA DE EMPRESAS 2020)","4":"CONSEJERIA DE ECONOMIA Y CONOCIMIENTO","5":"CENTROS CADE (CENTRO ANDALUZ DE EMPRENDIMIENTO)","6":"2016","7":"","8":"SI","9":"INST","10":"M\u00c1LAGA","11":"ANDALUCIA","12":"1","13":"","14":"","15":"1","16":"","17":"","18":"","19":"","20":"","21":"","22":"","23":"","24":"","25":"","26":"1","27":"","28":"","29":"","30":"1","31":"","32":"","33":"","34":"","35":"","36":"","37":"1","38":"","39":"","40":"","41":"","42":"","43":"","44":"","45":"","46":""},"4":{"0":"EMILIO J. MANSO","1":"9","2":"9.5","3":"PROGRAMA INNBIO-ADVANCE","4":"CONSEJERIA DE SALUD EN COLABORACION CON LA FUNDACION PARA LA INVESTIGACION BIOSANITARIA DE ANDALUCIA ORIENTAL (FIBAO) Y LA PARTICIPACION ECONOMICA DE LA FUNDACION CAJA RURAL Y CAJA GRANADA FUNDACION","5":"FIBAO Y EL INSTITUTO DE INVESTIGACION BIOMEDICA DE GRANADA (IBS GRANADA)","6":"2012","7":"ACTUALIDAD","8":"SI","9":"INST","10":"JAEN, ALMERIA Y GRANADA","11":"GRANADA, JAEN Y ALMERIA","12":"1","13":"","14":"","15":"","16":"","17":"","18":"1","19":"","20":"1","21":"1","22":"","23":"","24":"","25":"","26":"","27":"","28":"","29":"","30":"","31":"","32":"","33":"","34":"","35":"","36":"","37":"","38":"","39":"1","40":"","41":"","42":"","43":"","44":"","45":"","46":""},"5":{"0":"EMILIO J. MANSO","1":"9","2":"9.6","3":"PROGRAMA INNICIA CULTURA EMPRENDEDORA","4":"CONSEJERIA DE EDUCACION Y DEPORTE","5":"DIRECCION GENERAL DE INNOVACION Y FORMACION DEL PROFESORADO (955064195\/4320\/4191). GRUPO INNICIA (WHASTAPP 670942148). ANA BELEN GARCIA (ABGARCIA@ANDALUCIAEMPRENDE.ES). CULTURAEMPRENDEDORA.CED@JUNTADEANDALUCIA.ES","6":"2016","7":"ACTUALIDAD","8":"SI","9":"INST","10":"ANDALUCIA","11":"ANDALUCIA","12":"1","13":"1","14":"1","15":"1","16":"1","17":"1","18":"","19":"","20":"1","21":"1","22":"","23":"","24":"","25":"","26":"","27":"","28":"","29":"","30":"1","31":"","32":"","33":"1","34":"","35":"","36":"","37":"1","38":"","39":"","40":"","41":"","42":"","43":"1","44":"","45":"","46":""},"6":{"0":"EMILIO J. MANSO","1":"9","2":"9.7","3":"URBARURAL SOSTENIBLE","4":"CONSEJERIA DE AGRICULTURA, GANADERIA, PESCA Y DESARROLLO SOSTENIBLE","5":"ARA (ASOCIACION PARA EL DESARROLLO RURAL DE ANDALUCIA)","6":"2010","7":"","8":"SI","9":"INST","10":"ANDALUCIA","11":"ANDALUCIA","12":"","13":"","14":"","15":"1","16":"1","17":"","18":"1","19":"","20":"1","21":"","22":"","23":"1","24":"","25":"","26":"","27":"","28":"","29":"","30":"1","31":"","32":"","33":"","34":"","35":"1","36":"1","37":"1","38":"","39":"","40":"","41":"1","42":"","43":"","44":"1","45":"1","46":""},"7":{"0":"EMILIO J. MANSO","1":"9","2":"9.9","3":"ANDALUCIA LAB","4":"CONSEJERIA DE TURISMO, REGENERACI\u00d3N, JUSTICIA Y ADMINISTRACION LOCAL","5":"","6":"2015 (AUNQUE PUEDE QUE ANTES)","7":"ACTUALIDAD","8":"SI","9":"INST","10":"ANDALUCIA","11":"ANDALUCIA","12":"","13":"","14":"","15":"1","16":"","17":"","18":"1","19":"","20":"1","21":"","22":"","23":"","24":"","25":"","26":"1","27":"","28":"","29":"","30":"1","31":"","32":"","33":"","34":"","35":"","36":"","37":"1","38":"","39":"","40":"","41":"","42":"","43":"","44":"","45":"","46":""}}